
                    {
                    "@context": "http://www.shared-canvas.org/ns/context.json",
                    "@id": "http://demos.biblissima-condorcet.fr/iiif/metadata/BL_Add_10289/list/transscript_60r.json",
                    "@type": "sc:AnnotationList",
                    "resources":[    
                    
                    
                        
                        {
                        
                        "@id":"http://demos.biblissima-condorcet.fr/iiif/metadata/BL_Add_10289/Annotation/60r_line3815.json",
                        "@type":"oa:Annotation",
                        "motivation":"sc:painting",
                        "resource":{
                        "@type":"cnt:ContentAsText",
                        "chars":"Quant Hildebert abes esteit",
                        "format":"text/plain",
                        "language":"fr-FR"
                        },
                        
                        
                        "on":"http://sanddragon.bl.uk/IIIFMetadataService/canvas/folio-60r.json#xywh=1100,600,3500,200"
                        
                        }
                     ,    
                        {
                        
                        "@id":"http://demos.biblissima-condorcet.fr/iiif/metadata/BL_Add_10289/Annotation/60r_line3816.json",
                        "@type":"oa:Annotation",
                        "motivation":"sc:painting",
                        "resource":{
                        "@type":"cnt:ContentAsText",
                        "chars":"Del mont et poesté aveit,",
                        "format":"text/plain",
                        "language":"fr-FR"
                        },
                        
                        
                        "on":"http://sanddragon.bl.uk/IIIFMetadataService/canvas/folio-60r.json#xywh=1100,800,3500,200"
                        
                        }
                     ,    
                        {
                        
                        "@id":"http://demos.biblissima-condorcet.fr/iiif/metadata/BL_Add_10289/Annotation/60r_line3817.json",
                        "@type":"oa:Annotation",
                        "motivation":"sc:painting",
                        "resource":{
                        "@type":"cnt:ContentAsText",
                        "chars":"Out une fame en Normendie",
                        "format":"text/plain",
                        "language":"fr-FR"
                        },
                        
                        
                        "on":"http://sanddragon.bl.uk/IIIFMetadataService/canvas/folio-60r.json#xywh=1100,1000,3500,200"
                        
                        }
                     ,    
                        {
                        
                        "@id":"http://demos.biblissima-condorcet.fr/iiif/metadata/BL_Add_10289/Annotation/60r_line3818.json",
                        "@type":"oa:Annotation",
                        "motivation":"sc:painting",
                        "resource":{
                        "@type":"cnt:ContentAsText",
                        "chars":"Qui dotose ert molt de sa vie.",
                        "format":"text/plain",
                        "language":"fr-FR"
                        },
                        
                        
                        "on":"http://sanddragon.bl.uk/IIIFMetadataService/canvas/folio-60r.json#xywh=1100,1200,3500,200"
                        
                        }
                     ,    
                        {
                        
                        "@id":"http://demos.biblissima-condorcet.fr/iiif/metadata/BL_Add_10289/Annotation/60r_line3819.json",
                        "@type":"oa:Annotation",
                        "motivation":"sc:painting",
                        "resource":{
                        "@type":"cnt:ContentAsText",
                        "chars":"Enceinte esteit. A enfenter",
                        "format":"text/plain",
                        "language":"fr-FR"
                        },
                        
                        
                        "on":"http://sanddragon.bl.uk/IIIFMetadataService/canvas/folio-60r.json#xywh=1100,1400,3500,200"
                        
                        }
                     ,    
                        {
                        
                        "@id":"http://demos.biblissima-condorcet.fr/iiif/metadata/BL_Add_10289/Annotation/60r_line3820.json",
                        "@type":"oa:Annotation",
                        "motivation":"sc:painting",
                        "resource":{
                        "@type":"cnt:ContentAsText",
                        "chars":"Aveit poor de devier.",
                        "format":"text/plain",
                        "language":"fr-FR"
                        },
                        
                        
                        "on":"http://sanddragon.bl.uk/IIIFMetadataService/canvas/folio-60r.json#xywh=1100,1600,3500,200"
                        
                        }
                     ,    
                        {
                        
                        "@id":"http://demos.biblissima-condorcet.fr/iiif/metadata/BL_Add_10289/Annotation/60r_line3821.json",
                        "@type":"oa:Annotation",
                        "motivation":"sc:painting",
                        "resource":{
                        "@type":"cnt:ContentAsText",
                        "chars":"Ele preia a son seignor,",
                        "format":"text/plain",
                        "language":"fr-FR"
                        },
                        
                        
                        "on":"http://sanddragon.bl.uk/IIIFMetadataService/canvas/folio-60r.json#xywh=1100,1800,3500,200"
                        
                        }
                     ,    
                        {
                        
                        "@id":"http://demos.biblissima-condorcet.fr/iiif/metadata/BL_Add_10289/Annotation/60r_line3822.json",
                        "@type":"oa:Annotation",
                        "motivation":"sc:painting",
                        "resource":{
                        "@type":"cnt:ContentAsText",
                        "chars":"Molt dolcement et par amor,",
                        "format":"text/plain",
                        "language":"fr-FR"
                        },
                        
                        
                        "on":"http://sanddragon.bl.uk/IIIFMetadataService/canvas/folio-60r.json#xywh=1100,2000,3500,200"
                        
                        }
                     ,    
                        {
                        
                        "@id":"http://demos.biblissima-condorcet.fr/iiif/metadata/BL_Add_10289/Annotation/60r_line3823.json",
                        "@type":"oa:Annotation",
                        "motivation":"sc:painting",
                        "resource":{
                        "@type":"cnt:ContentAsText",
                        "chars":"Que, si li plaist, congié li dont,",
                        "format":"text/plain",
                        "language":"fr-FR"
                        },
                        
                        
                        "on":"http://sanddragon.bl.uk/IIIFMetadataService/canvas/folio-60r.json#xywh=1100,2200,3500,200"
                        
                        }
                     ,    
                        {
                        
                        "@id":"http://demos.biblissima-condorcet.fr/iiif/metadata/BL_Add_10289/Annotation/60r_line3824.json",
                        "@type":"oa:Annotation",
                        "motivation":"sc:painting",
                        "resource":{
                        "@type":"cnt:ContentAsText",
                        "chars":"Ainz qu’ait enfant, d’aler au mont",
                        "format":"text/plain",
                        "language":"fr-FR"
                        },
                        
                        
                        "on":"http://sanddragon.bl.uk/IIIFMetadataService/canvas/folio-60r.json#xywh=1100,2400,3500,200"
                        
                        }
                     ,    
                        {
                        
                        "@id":"http://demos.biblissima-condorcet.fr/iiif/metadata/BL_Add_10289/Annotation/60r_line3825.json",
                        "@type":"oa:Annotation",
                        "motivation":"sc:painting",
                        "resource":{
                        "@type":"cnt:ContentAsText",
                        "chars":"A oreisons, quer grant talent",
                        "format":"text/plain",
                        "language":"fr-FR"
                        },
                        
                        
                        "on":"http://sanddragon.bl.uk/IIIFMetadataService/canvas/folio-60r.json#xywh=1100,2600,3500,200"
                        
                        }
                     ,    
                        {
                        
                        "@id":"http://demos.biblissima-condorcet.fr/iiif/metadata/BL_Add_10289/Annotation/60r_line3826.json",
                        "@type":"oa:Annotation",
                        "motivation":"sc:painting",
                        "resource":{
                        "@type":"cnt:ContentAsText",
                        "chars":"L’en esteit pris novelement  :",
                        "format":"text/plain",
                        "language":"fr-FR"
                        },
                        
                        
                        "on":"http://sanddragon.bl.uk/IIIFMetadataService/canvas/folio-60r.json#xywh=1100,2800,3500,200"
                        
                        }
                     ,    
                        {
                        
                        "@id":"http://demos.biblissima-condorcet.fr/iiif/metadata/BL_Add_10289/Annotation/60r_line3827.json",
                        "@type":"oa:Annotation",
                        "motivation":"sc:painting",
                        "resource":{
                        "@type":"cnt:ContentAsText",
                        "chars":"Augent emsemble, cen diseit.",
                        "format":"text/plain",
                        "language":"fr-FR"
                        },
                        
                        
                        "on":"http://sanddragon.bl.uk/IIIFMetadataService/canvas/folio-60r.json#xywh=1100,3000,3500,200"
                        
                        }
                     ,    
                        {
                        
                        "@id":"http://demos.biblissima-condorcet.fr/iiif/metadata/BL_Add_10289/Annotation/60r_line3828.json",
                        "@type":"oa:Annotation",
                        "motivation":"sc:painting",
                        "resource":{
                        "@type":"cnt:ContentAsText",
                        "chars":"Il li respont que non fereit  :",
                        "format":"text/plain",
                        "language":"fr-FR"
                        },
                        
                        
                        "on":"http://sanddragon.bl.uk/IIIFMetadataService/canvas/folio-60r.json#xywh=1100,3200,3500,200"
                        
                        }
                     ,    
                        {
                        
                        "@id":"http://demos.biblissima-condorcet.fr/iiif/metadata/BL_Add_10289/Annotation/60r_line3829.json",
                        "@type":"oa:Annotation",
                        "motivation":"sc:painting",
                        "resource":{
                        "@type":"cnt:ContentAsText",
                        "chars":"Atende, et souffre, asez ira",
                        "format":"text/plain",
                        "language":"fr-FR"
                        },
                        
                        
                        "on":"http://sanddragon.bl.uk/IIIFMetadataService/canvas/folio-60r.json#xywh=1100,3400,3500,200"
                        
                        }
                     ,    
                        {
                        
                        "@id":"http://demos.biblissima-condorcet.fr/iiif/metadata/BL_Add_10289/Annotation/60r_line3830.json",
                        "@type":"oa:Annotation",
                        "motivation":"sc:painting",
                        "resource":{
                        "@type":"cnt:ContentAsText",
                        "chars":"Emprof icen qu’enfant aura.",
                        "format":"text/plain",
                        "language":"fr-FR"
                        },
                        
                        
                        "on":"http://sanddragon.bl.uk/IIIFMetadataService/canvas/folio-60r.json#xywh=1100,3600,3500,200"
                        
                        }
                     ,    
                        {
                        
                        "@id":"http://demos.biblissima-condorcet.fr/iiif/metadata/BL_Add_10289/Annotation/60r_line3831.json",
                        "@type":"oa:Annotation",
                        "motivation":"sc:painting",
                        "resource":{
                        "@type":"cnt:ContentAsText",
                        "chars":"« N’est or de cen nule seison,",
                        "format":"text/plain",
                        "language":"fr-FR"
                        },
                        
                        
                        "on":"http://sanddragon.bl.uk/IIIFMetadataService/canvas/folio-60r.json#xywh=1100,3800,3500,200"
                        
                        }
                     ,    
                        {
                        
                        "@id":"http://demos.biblissima-condorcet.fr/iiif/metadata/BL_Add_10289/Annotation/60r_line3832.json",
                        "@type":"oa:Annotation",
                        "motivation":"sc:painting",
                        "resource":{
                        "@type":"cnt:ContentAsText",
                        "chars":"Dist li prodom, asez iron ».",
                        "format":"text/plain",
                        "language":"fr-FR"
                        },
                        
                        
                        "on":"http://sanddragon.bl.uk/IIIFMetadataService/canvas/folio-60r.json#xywh=1100,4000,3500,200"
                        
                        }
                     ,    
                        {
                        
                        "@id":"http://demos.biblissima-condorcet.fr/iiif/metadata/BL_Add_10289/Annotation/60r_line3833.json",
                        "@type":"oa:Annotation",
                        "motivation":"sc:painting",
                        "resource":{
                        "@type":"cnt:ContentAsText",
                        "chars":"Quant la dame vit qu’el n’aureit",
                        "format":"text/plain",
                        "language":"fr-FR"
                        },
                        
                        
                        "on":"http://sanddragon.bl.uk/IIIFMetadataService/canvas/folio-60r.json#xywh=1100,4200,3500,200"
                        
                        }
                     ,    
                        {
                        
                        "@id":"http://demos.biblissima-condorcet.fr/iiif/metadata/BL_Add_10289/Annotation/60r_line3834.json",
                        "@type":"oa:Annotation",
                        "motivation":"sc:painting",
                        "resource":{
                        "@type":"cnt:ContentAsText",
                        "chars":"Congié de cen qu’el requiereit,",
                        "format":"text/plain",
                        "language":"fr-FR"
                        },
                        
                        
                        "on":"http://sanddragon.bl.uk/IIIFMetadataService/canvas/folio-60r.json#xywh=1100,4400,3500,200"
                        
                        }
                     ,    
                        {
                        
                        "@id":"http://demos.biblissima-condorcet.fr/iiif/metadata/BL_Add_10289/Annotation/60r_line3835.json",
                        "@type":"oa:Annotation",
                        "motivation":"sc:painting",
                        "resource":{
                        "@type":"cnt:ContentAsText",
                        "chars":"Greignor talent idonc l’emprist",
                        "format":"text/plain",
                        "language":"fr-FR"
                        },
                        
                        
                        "on":"http://sanddragon.bl.uk/IIIFMetadataService/canvas/folio-60r.json#xywh=1100,4600,3500,200"
                        
                        }
                     ,    
                        {
                        
                        "@id":"http://demos.biblissima-condorcet.fr/iiif/metadata/BL_Add_10289/Annotation/60r_line3836.json",
                        "@type":"oa:Annotation",
                        "motivation":"sc:painting",
                        "resource":{
                        "@type":"cnt:ContentAsText",
                        "chars":"Et son seignor souvent requist  :",
                        "format":"text/plain",
                        "language":"fr-FR"
                        },
                        
                        
                        "on":"http://sanddragon.bl.uk/IIIFMetadataService/canvas/folio-60r.json#xywh=1100,4800,3500,200"
                        
                        }
                     ,    
                        {
                        
                        "@id":"http://demos.biblissima-condorcet.fr/iiif/metadata/BL_Add_10289/Annotation/60r_line3837.json",
                        "@type":"oa:Annotation",
                        "motivation":"sc:painting",
                        "resource":{
                        "@type":"cnt:ContentAsText",
                        "chars":"Tant l’a preié que veincu l’a.",
                        "format":"text/plain",
                        "language":"fr-FR"
                        },
                        
                        
                        "on":"http://sanddragon.bl.uk/IIIFMetadataService/canvas/folio-60r.json#xywh=1100,5000,3500,200"
                        
                        }
                     ,    
                        {
                        
                        "@id":"http://demos.biblissima-condorcet.fr/iiif/metadata/BL_Add_10289/Annotation/60r_line3838.json",
                        "@type":"oa:Annotation",
                        "motivation":"sc:painting",
                        "resource":{
                        "@type":"cnt:ContentAsText",
                        "chars":"Lor eirre cil tost apresta  ;",
                        "format":"text/plain",
                        "language":"fr-FR"
                        },
                        
                        
                        "on":"http://sanddragon.bl.uk/IIIFMetadataService/canvas/folio-60r.json#xywh=1100,5200,3500,200"
                        
                        }
                     ,    
                        {
                        
                        "@id":"http://demos.biblissima-condorcet.fr/iiif/metadata/BL_Add_10289/Annotation/60r_line3839.json",
                        "@type":"oa:Annotation",
                        "motivation":"sc:painting",
                        "resource":{
                        "@type":"cnt:ContentAsText",
                        "chars":"De ses serjanz a cil menei.",
                        "format":"text/plain",
                        "language":"fr-FR"
                        },
                        
                        
                        "on":"http://sanddragon.bl.uk/IIIFMetadataService/canvas/folio-60r.json#xywh=1100,5400,3500,200"
                        
                        }
                     ,    
                        {
                        
                        "@id":"http://demos.biblissima-condorcet.fr/iiif/metadata/BL_Add_10289/Annotation/60r_line3840.json",
                        "@type":"oa:Annotation",
                        "motivation":"sc:painting",
                        "resource":{
                        "@type":"cnt:ContentAsText",
                        "chars":"Al mont vienent, tant unt esré.",
                        "format":"text/plain",
                        "language":"fr-FR"
                        },
                        
                        
                        "on":"http://sanddragon.bl.uk/IIIFMetadataService/canvas/folio-60r.json#xywh=1100,5600,3500,200"
                        
                        }
                     ,    
                        {
                        
                        "@id":"http://demos.biblissima-condorcet.fr/iiif/metadata/BL_Add_10289/Annotation/60r_line3841.json",
                        "@type":"oa:Annotation",
                        "motivation":"sc:painting",
                        "resource":{
                        "@type":"cnt:ContentAsText",
                        "chars":"Quant ourent fait lor oreisons",
                        "format":"text/plain",
                        "language":"fr-FR"
                        },
                        
                        
                        "on":"http://sanddragon.bl.uk/IIIFMetadataService/canvas/folio-60r.json#xywh=1100,5800,3500,200"
                        
                        }
                     ,    
                        {
                        
                        "@id":"http://demos.biblissima-condorcet.fr/iiif/metadata/BL_Add_10289/Annotation/60r_line3842.json",
                        "@type":"oa:Annotation",
                        "motivation":"sc:painting",
                        "resource":{
                        "@type":"cnt:ContentAsText",
                        "chars":"Devotement, a genoillons,",
                        "format":"text/plain",
                        "language":"fr-FR"
                        },
                        
                        
                        "on":"http://sanddragon.bl.uk/IIIFMetadataService/canvas/folio-60r.json#xywh=1100,6000,3500,200"
                        
                        }
                     ,    
                        {
                        
                        "@id":"http://demos.biblissima-condorcet.fr/iiif/metadata/BL_Add_10289/Annotation/60r_line3843.json",
                        "@type":"oa:Annotation",
                        "motivation":"sc:painting",
                        "resource":{
                        "@type":"cnt:ContentAsText",
                        "chars":"Et lor offrende au mestre autel",
                        "format":"text/plain",
                        "language":"fr-FR"
                        },
                        
                        
                        "on":"http://sanddragon.bl.uk/IIIFMetadataService/canvas/folio-60r.json#xywh=1100,6200,3500,200"
                        
                        }
                     ,    
                        {
                        
                        "@id":"http://demos.biblissima-condorcet.fr/iiif/metadata/BL_Add_10289/Annotation/60r_line3844.json",
                        "@type":"oa:Annotation",
                        "motivation":"sc:painting",
                        "resource":{
                        "@type":"cnt:ContentAsText",
                        "chars":"Et par les autres autretel,",
                        "format":"text/plain",
                        "language":"fr-FR"
                        },
                        
                        
                        "on":"http://sanddragon.bl.uk/IIIFMetadataService/canvas/folio-60r.json#xywh=1100,6400,3500,200"
                        
                        }
                    
                    ]
                    }
                