
                    {
                    "@context": "http://www.shared-canvas.org/ns/context.json",
                    "@id": "http://demos.biblissima-condorcet.fr/iiif/metadata/BL_Add_10289/list/transscript_32r.json",
                    "@type": "sc:AnnotationList",
                    "resources":[    
                    
                    
                        
                        {
                        
                        "@id":"http://demos.biblissima-condorcet.fr/iiif/metadata/BL_Add_10289/Annotation/32r_line1859.json",
                        "@type":"oa:Annotation",
                        "motivation":"sc:painting",
                        "resource":{
                        "@type":"cnt:ContentAsText",
                        "chars":"A lui vienent priveement,",
                        "format":"text/plain",
                        "language":"fr-FR"
                        },
                        
                        
                        "on":"http://sanddragon.bl.uk/IIIFMetadataService/canvas/folio-32r.json#xywh=500,500,4000,213"
                        
                        }
                     ,    
                        {
                        
                        "@id":"http://demos.biblissima-condorcet.fr/iiif/metadata/BL_Add_10289/Annotation/32r_line1860.json",
                        "@type":"oa:Annotation",
                        "motivation":"sc:painting",
                        "resource":{
                        "@type":"cnt:ContentAsText",
                        "chars":"Si lor a dit celeement",
                        "format":"text/plain",
                        "language":"fr-FR"
                        },
                        
                        
                        "on":"http://sanddragon.bl.uk/IIIFMetadataService/canvas/folio-32r.json#xywh=500,713,4000,213"
                        
                        }
                     ,    
                        {
                        
                        "@id":"http://demos.biblissima-condorcet.fr/iiif/metadata/BL_Add_10289/Annotation/32r_line1861.json",
                        "@type":"oa:Annotation",
                        "motivation":"sc:painting",
                        "resource":{
                        "@type":"cnt:ContentAsText",
                        "chars":"Qu’il le seuvent la ou ira,",
                        "format":"text/plain",
                        "language":"fr-FR"
                        },
                        
                        
                        "on":"http://sanddragon.bl.uk/IIIFMetadataService/canvas/folio-32r.json#xywh=500,926,4000,213"
                        
                        }
                     ,    
                        {
                        
                        "@id":"http://demos.biblissima-condorcet.fr/iiif/metadata/BL_Add_10289/Annotation/32r_line1862.json",
                        "@type":"oa:Annotation",
                        "motivation":"sc:painting",
                        "resource":{
                        "@type":"cnt:ContentAsText",
                        "chars":"Isnelement ; pois lor dira",
                        "format":"text/plain",
                        "language":"fr-FR"
                        },
                        
                        
                        "on":"http://sanddragon.bl.uk/IIIFMetadataService/canvas/folio-32r.json#xywh=500,1139,4000,213"
                        
                        }
                     ,    
                        {
                        
                        "@id":"http://demos.biblissima-condorcet.fr/iiif/metadata/BL_Add_10289/Annotation/32r_line1863.json",
                        "@type":"oa:Annotation",
                        "motivation":"sc:painting",
                        "resource":{
                        "@type":"cnt:ContentAsText",
                        "chars":"Por quei les a a sei mandeiz",
                        "format":"text/plain",
                        "language":"fr-FR"
                        },
                        
                        
                        "on":"http://sanddragon.bl.uk/IIIFMetadataService/canvas/folio-32r.json#xywh=500,1352,4000,213"
                        
                        }
                     ,    
                        {
                        
                        "@id":"http://demos.biblissima-condorcet.fr/iiif/metadata/BL_Add_10289/Annotation/32r_line1864.json",
                        "@type":"oa:Annotation",
                        "motivation":"sc:painting",
                        "resource":{
                        "@type":"cnt:ContentAsText",
                        "chars":"De tantes parz et aünez.",
                        "format":"text/plain",
                        "language":"fr-FR"
                        },
                        
                        
                        "on":"http://sanddragon.bl.uk/IIIFMetadataService/canvas/folio-32r.json#xywh=500,1565,4000,213"
                        
                        }
                     ,    
                        {
                        
                        "@id":"http://demos.biblissima-condorcet.fr/iiif/metadata/BL_Add_10289/Annotation/32r_line1865.json",
                        "@type":"oa:Annotation",
                        "motivation":"sc:painting",
                        "resource":{
                        "@type":"cnt:ContentAsText",
                        "chars":"Il n’i a plus, il est meüz",
                        "format":"text/plain",
                        "language":"fr-FR"
                        },
                        
                        
                        "on":"http://sanddragon.bl.uk/IIIFMetadataService/canvas/folio-32r.json#xywh=500,1778,4000,213"
                        
                        }
                     ,    
                        {
                        
                        "@id":"http://demos.biblissima-condorcet.fr/iiif/metadata/BL_Add_10289/Annotation/32r_line1866.json",
                        "@type":"oa:Annotation",
                        "motivation":"sc:painting",
                        "resource":{
                        "@type":"cnt:ContentAsText",
                        "chars":"Mes sis erres fut tot seüz.",
                        "format":"text/plain",
                        "language":"fr-FR"
                        },
                        
                        
                        "on":"http://sanddragon.bl.uk/IIIFMetadataService/canvas/folio-32r.json#xywh=500,1991,4000,213"
                        
                        }
                     ,    
                        {
                        
                        "@id":"http://demos.biblissima-condorcet.fr/iiif/metadata/BL_Add_10289/Annotation/32r_line1867.json",
                        "@type":"oa:Annotation",
                        "motivation":"sc:painting",
                        "resource":{
                        "@type":"cnt:ContentAsText",
                        "chars":"A Avrenches vint belement",
                        "format":"text/plain",
                        "language":"fr-FR"
                        },
                        
                        
                        "on":"http://sanddragon.bl.uk/IIIFMetadataService/canvas/folio-32r.json#xywh=500,2204,4000,213"
                        
                        }
                     ,    
                        {
                        
                        "@id":"http://demos.biblissima-condorcet.fr/iiif/metadata/BL_Add_10289/Annotation/32r_line1868.json",
                        "@type":"oa:Annotation",
                        "motivation":"sc:painting",
                        "resource":{
                        "@type":"cnt:ContentAsText",
                        "chars":"Si cum de cen ne fust neient.",
                        "format":"text/plain",
                        "language":"fr-FR"
                        },
                        
                        
                        "on":"http://sanddragon.bl.uk/IIIFMetadataService/canvas/folio-32r.json#xywh=500,2417,4000,213"
                        
                        }
                     ,    
                        {
                        
                        "@id":"http://demos.biblissima-condorcet.fr/iiif/metadata/BL_Add_10289/Annotation/32r_line1869.json",
                        "@type":"oa:Annotation",
                        "motivation":"sc:painting",
                        "resource":{
                        "@type":"cnt:ContentAsText",
                        "chars":"Semblant faiseit que il queisist",
                        "format":"text/plain",
                        "language":"fr-FR"
                        },
                        
                        
                        "on":"http://sanddragon.bl.uk/IIIFMetadataService/canvas/folio-32r.json#xywh=500,2630,4000,213"
                        
                        }
                     ,    
                        {
                        
                        "@id":"http://demos.biblissima-condorcet.fr/iiif/metadata/BL_Add_10289/Annotation/32r_line1870.json",
                        "@type":"oa:Annotation",
                        "motivation":"sc:painting",
                        "resource":{
                        "@type":"cnt:ContentAsText",
                        "chars":"Tote altre rien que il ne fist.",
                        "format":"text/plain",
                        "language":"fr-FR"
                        },
                        
                        
                        "on":"http://sanddragon.bl.uk/IIIFMetadataService/canvas/folio-32r.json#xywh=500,2843,4000,213"
                        
                        }
                     ,    
                        {
                        
                        "@id":"http://demos.biblissima-condorcet.fr/iiif/metadata/BL_Add_10289/Annotation/32r_line1871.json",
                        "@type":"oa:Annotation",
                        "motivation":"sc:painting",
                        "resource":{
                        "@type":"cnt:ContentAsText",
                        "chars":"Quant il vint la, primes parla",
                        "format":"text/plain",
                        "language":"fr-FR"
                        },
                        
                        
                        "on":"http://sanddragon.bl.uk/IIIFMetadataService/canvas/folio-32r.json#xywh=500,3056,4000,213"
                        
                        }
                     ,    
                        {
                        
                        "@id":"http://demos.biblissima-condorcet.fr/iiif/metadata/BL_Add_10289/Annotation/32r_line1872.json",
                        "@type":"oa:Annotation",
                        "motivation":"sc:painting",
                        "resource":{
                        "@type":"cnt:ContentAsText",
                        "chars":"D’altres choses, puis apela",
                        "format":"text/plain",
                        "language":"fr-FR"
                        },
                        
                        
                        "on":"http://sanddragon.bl.uk/IIIFMetadataService/canvas/folio-32r.json#xywh=500,3269,4000,213"
                        
                        }
                     ,    
                        {
                        
                        "@id":"http://demos.biblissima-condorcet.fr/iiif/metadata/BL_Add_10289/Annotation/32r_line1873.json",
                        "@type":"oa:Annotation",
                        "motivation":"sc:painting",
                        "resource":{
                        "@type":"cnt:ContentAsText",
                        "chars":"Vns vel baron qu’iluec esteit :",
                        "format":"text/plain",
                        "language":"fr-FR"
                        },
                        
                        
                        "on":"http://sanddragon.bl.uk/IIIFMetadataService/canvas/folio-32r.json#xywh=500,3482,4000,213"
                        
                        }
                     ,    
                        {
                        
                        "@id":"http://demos.biblissima-condorcet.fr/iiif/metadata/BL_Add_10289/Annotation/32r_line1874.json",
                        "@type":"oa:Annotation",
                        "motivation":"sc:painting",
                        "resource":{
                        "@type":"cnt:ContentAsText",
                        "chars":"Sis privez eirt, molt chier l’aveit  ;",
                        "format":"text/plain",
                        "language":"fr-FR"
                        },
                        
                        
                        "on":"http://sanddragon.bl.uk/IIIFMetadataService/canvas/folio-32r.json#xywh=500,3695,4000,213"
                        
                        }
                     ,    
                        {
                        
                        "@id":"http://demos.biblissima-condorcet.fr/iiif/metadata/BL_Add_10289/Annotation/32r_line1875.json",
                        "@type":"oa:Annotation",
                        "motivation":"sc:painting",
                        "resource":{
                        "@type":"cnt:ContentAsText",
                        "chars":"Commanda li que il alast",
                        "format":"text/plain",
                        "language":"fr-FR"
                        },
                        
                        
                        "on":"http://sanddragon.bl.uk/IIIFMetadataService/canvas/folio-32r.json#xywh=500,3908,4000,213"
                        
                        }
                     ,    
                        {
                        
                        "@id":"http://demos.biblissima-condorcet.fr/iiif/metadata/BL_Add_10289/Annotation/32r_line1876.json",
                        "@type":"oa:Annotation",
                        "motivation":"sc:painting",
                        "resource":{
                        "@type":"cnt:ContentAsText",
                        "chars":"Molt tost al mont et si rovast",
                        "format":"text/plain",
                        "language":"fr-FR"
                        },
                        
                        
                        "on":"http://sanddragon.bl.uk/IIIFMetadataService/canvas/folio-32r.json#xywh=500,4121,4000,213"
                        
                        }
                     ,    
                        {
                        
                        "@id":"http://demos.biblissima-condorcet.fr/iiif/metadata/BL_Add_10289/Annotation/32r_line1877.json",
                        "@type":"oa:Annotation",
                        "motivation":"sc:painting",
                        "resource":{
                        "@type":"cnt:ContentAsText",
                        "chars":"As chanoines muer lor vie ;",
                        "format":"text/plain",
                        "language":"fr-FR"
                        },
                        
                        
                        "on":"http://sanddragon.bl.uk/IIIFMetadataService/canvas/folio-32r.json#xywh=500,4334,4000,213"
                        
                        }
                     ,    
                        {
                        
                        "@id":"http://demos.biblissima-condorcet.fr/iiif/metadata/BL_Add_10289/Annotation/32r_line1878.json",
                        "@type":"oa:Annotation",
                        "motivation":"sc:painting",
                        "resource":{
                        "@type":"cnt:ContentAsText",
                        "chars":"Si ne leist pas qu’il ne lor die",
                        "format":"text/plain",
                        "language":"fr-FR"
                        },
                        
                        
                        "on":"http://sanddragon.bl.uk/IIIFMetadataService/canvas/folio-32r.json#xywh=500,4547,4000,213"
                        
                        }
                     ,    
                        {
                        
                        "@id":"http://demos.biblissima-condorcet.fr/iiif/metadata/BL_Add_10289/Annotation/32r_line1879.json",
                        "@type":"oa:Annotation",
                        "motivation":"sc:painting",
                        "resource":{
                        "@type":"cnt:ContentAsText",
                        "chars":"Moines deviengent, cen voleit,",
                        "format":"text/plain",
                        "language":"fr-FR"
                        },
                        
                        
                        "on":"http://sanddragon.bl.uk/IIIFMetadataService/canvas/folio-32r.json#xywh=500,4760,4000,213"
                        
                        }
                     ,    
                        {
                        
                        "@id":"http://demos.biblissima-condorcet.fr/iiif/metadata/BL_Add_10289/Annotation/32r_line1880.json",
                        "@type":"oa:Annotation",
                        "motivation":"sc:painting",
                        "resource":{
                        "@type":"cnt:ContentAsText",
                        "chars":"En lor mostier, qui bel esteit,",
                        "format":"text/plain",
                        "language":"fr-FR"
                        },
                        
                        
                        "on":"http://sanddragon.bl.uk/IIIFMetadataService/canvas/folio-32r.json#xywh=500,4973,4000,213"
                        
                        }
                     ,    
                        {
                        
                        "@id":"http://demos.biblissima-condorcet.fr/iiif/metadata/BL_Add_10289/Annotation/32r_line1881.json",
                        "@type":"oa:Annotation",
                        "motivation":"sc:painting",
                        "resource":{
                        "@type":"cnt:ContentAsText",
                        "chars":"Ou cen que non, si augent fors,",
                        "format":"text/plain",
                        "language":"fr-FR"
                        },
                        
                        
                        "on":"http://sanddragon.bl.uk/IIIFMetadataService/canvas/folio-32r.json#xywh=500,5186,4000,213"
                        
                        }
                     ,    
                        {
                        
                        "@id":"http://demos.biblissima-condorcet.fr/iiif/metadata/BL_Add_10289/Annotation/32r_line1882.json",
                        "@type":"oa:Annotation",
                        "motivation":"sc:painting",
                        "resource":{
                        "@type":"cnt:ContentAsText",
                        "chars":"Lor dras enportent et lor cors,",
                        "format":"text/plain",
                        "language":"fr-FR"
                        },
                        
                        
                        "on":"http://sanddragon.bl.uk/IIIFMetadataService/canvas/folio-32r.json#xywh=500,5399,4000,213"
                        
                        }
                     ,    
                        {
                        
                        "@id":"http://demos.biblissima-condorcet.fr/iiif/metadata/BL_Add_10289/Annotation/32r_line1883.json",
                        "@type":"oa:Annotation",
                        "motivation":"sc:painting",
                        "resource":{
                        "@type":"cnt:ContentAsText",
                        "chars":"Tant solement, et nient plus :",
                        "format":"text/plain",
                        "language":"fr-FR"
                        },
                        
                        
                        "on":"http://sanddragon.bl.uk/IIIFMetadataService/canvas/folio-32r.json#xywh=500,5612,4000,213"
                        
                        }
                     ,    
                        {
                        
                        "@id":"http://demos.biblissima-condorcet.fr/iiif/metadata/BL_Add_10289/Annotation/32r_line1884.json",
                        "@type":"oa:Annotation",
                        "motivation":"sc:painting",
                        "resource":{
                        "@type":"cnt:ContentAsText",
                        "chars":"Marriz esteit od els li dus.",
                        "format":"text/plain",
                        "language":"fr-FR"
                        },
                        
                        
                        "on":"http://sanddragon.bl.uk/IIIFMetadataService/canvas/folio-32r.json#xywh=500,5825,4000,213"
                        
                        }
                     ,    
                        {
                        
                        "@id":"http://demos.biblissima-condorcet.fr/iiif/metadata/BL_Add_10289/Annotation/32r_line1885.json",
                        "@type":"oa:Annotation",
                        "motivation":"sc:painting",
                        "resource":{
                        "@type":"cnt:ContentAsText",
                        "chars":"Emprés li dist qu’il demandast",
                        "format":"text/plain",
                        "language":"fr-FR"
                        },
                        
                        
                        "on":"http://sanddragon.bl.uk/IIIFMetadataService/canvas/folio-32r.json#xywh=500,6038,4000,213"
                        
                        }
                     ,    
                        {
                        
                        "@id":"http://demos.biblissima-condorcet.fr/iiif/metadata/BL_Add_10289/Annotation/32r_line1886.json",
                        "@type":"oa:Annotation",
                        "motivation":"sc:painting",
                        "resource":{
                        "@type":"cnt:ContentAsText",
                        "chars":"Totes les cleis et sis guardast,",
                        "format":"text/plain",
                        "language":"fr-FR"
                        },
                        
                        
                        "on":"http://sanddragon.bl.uk/IIIFMetadataService/canvas/folio-32r.json#xywh=500,6251,4000,213"
                        
                        }
                     ,    
                        {
                        
                        "@id":"http://demos.biblissima-condorcet.fr/iiif/metadata/BL_Add_10289/Annotation/32r_line1887.json",
                        "@type":"oa:Annotation",
                        "motivation":"sc:painting",
                        "resource":{
                        "@type":"cnt:ContentAsText",
                        "chars":"Le tresor, tot l’or et l’argent,",
                        "format":"text/plain",
                        "language":"fr-FR"
                        },
                        
                        
                        "on":"http://sanddragon.bl.uk/IIIFMetadataService/canvas/folio-32r.json#xywh=500,6464,4000,213"
                        
                        }
                     ,    
                        {
                        
                        "@id":"http://demos.biblissima-condorcet.fr/iiif/metadata/BL_Add_10289/Annotation/32r_line1888.json",
                        "@type":"oa:Annotation",
                        "motivation":"sc:painting",
                        "resource":{
                        "@type":"cnt:ContentAsText",
                        "chars":"Les altres choses ensement.",
                        "format":"text/plain",
                        "language":"fr-FR"
                        },
                        
                        
                        "on":"http://sanddragon.bl.uk/IIIFMetadataService/canvas/folio-32r.json#xywh=500,6677,4000,213"
                        
                        }
                    
                    ]
                    }
                